{
    "sourceFile": "package.json",
    "activeCommit": 0,
    "commits": [
        {
            "activePatchIndex": 7,
            "patches": [
                {
                    "date": 1721482424228,
                    "content": "Index: \n===================================================================\n--- \n+++ \n"
                },
                {
                    "date": 1722078211254,
                    "content": "Index: \n===================================================================\n--- \n+++ \n@@ -23,9 +23,9 @@\n     \"@angular/platform-browser-dynamic\": \"^17.3.0\",\n     \"@angular/platform-server\": \"^17.3.0\",\n     \"@angular/router\": \"^17.3.0\",\n     \"@angular/ssr\": \"^17.3.8\",\n-    \"@types/socket.io-client\": \"^3.0.0\",\n+    \"@types/socket.io-client\": \"^4.7.0\",\n     \"core-js\": \"^3.37.1\",\n     \"express\": \"^4.18.2\",\n     \"moment-timezone\": \"^0.5.45\",\n     \"rxjs\": \"~7.8.0\",\n"
                },
                {
                    "date": 1722078257388,
                    "content": "Index: \n===================================================================\n--- \n+++ \n@@ -23,9 +23,9 @@\n     \"@angular/platform-browser-dynamic\": \"^17.3.0\",\n     \"@angular/platform-server\": \"^17.3.0\",\n     \"@angular/router\": \"^17.3.0\",\n     \"@angular/ssr\": \"^17.3.8\",\n-    \"@types/socket.io-client\": \"^4.7.0\",\n+    \"@types/socket.io-client\": \"^3.0.0\",\n     \"core-js\": \"^3.37.1\",\n     \"express\": \"^4.18.2\",\n     \"moment-timezone\": \"^0.5.45\",\n     \"rxjs\": \"~7.8.0\",\n"
                },
                {
                    "date": 1722078449347,
                    "content": "Index: \n===================================================================\n--- \n+++ \n@@ -5,47 +5,42 @@\n     \"ng\": \"ng\",\n     \"start\": \"ng serve\",\n     \"build\": \"ng build\",\n     \"watch\": \"ng build --watch --configuration development\",\n-    \"test\": \"ng test\",\n-    \"serve:ssr:taxt-Backend\": \"node dist/taxt-backend/server/server.mjs\"\n+    \"test\": \"ng test\"\n   },\n   \"private\": true,\n   \"dependencies\": {\n-    \"@angular/animations\": \"^17.3.0\",\n-    \"@angular/cdk\": \"^17.3.10\",\n-    \"@angular/common\": \"^17.3.0\",\n-    \"@angular/compiler\": \"^17.3.0\",\n-    \"@angular/core\": \"^17.3.0\",\n+    \"@angular/animations\": \"^16.2.0\",\n+    \"@angular/cdk\": \"^16.2.7\",\n+    \"@angular/common\": \"^16.2.0\",\n+    \"@angular/compiler\": \"^16.2.0\",\n+    \"@angular/core\": \"^16.2.0\",\n     \"@angular/flex-layout\": \"^15.0.0-beta.42\",\n-    \"@angular/forms\": \"^17.3.0\",\n-    \"@angular/material\": \"^17.3.10\",\n-    \"@angular/platform-browser\": \"^17.3.0\",\n-    \"@angular/platform-browser-dynamic\": \"^17.3.0\",\n-    \"@angular/platform-server\": \"^17.3.0\",\n-    \"@angular/router\": \"^17.3.0\",\n-    \"@angular/ssr\": \"^17.3.8\",\n+    \"@angular/forms\": \"^16.2.0\",\n+    \"@angular/google-maps\": \"^17.0.1\",\n+    \"@angular/material\": \"^16.2.7\",\n+    \"@angular/platform-browser\": \"^16.2.0\",\n+    \"@angular/platform-browser-dynamic\": \"^16.2.0\",\n+    \"@angular/router\": \"^16.2.0\",\n     \"@types/socket.io-client\": \"^3.0.0\",\n-    \"core-js\": \"^3.37.1\",\n-    \"express\": \"^4.18.2\",\n-    \"moment-timezone\": \"^0.5.45\",\n+    \"core-js\": \"^3.33.2\",\n+    \"moment-timezone\": \"^0.5.43\",\n     \"rxjs\": \"~7.8.0\",\n     \"rxjs-compat\": \"^6.6.7\",\n     \"tslib\": \"^2.3.0\",\n-    \"zone.js\": \"~0.14.3\"\n+    \"zone.js\": \"~0.13.0\"\n   },\n   \"devDependencies\": {\n-    \"@angular-devkit/build-angular\": \"^17.3.8\",\n-    \"@angular/cli\": \"^17.3.8\",\n-    \"@angular/compiler-cli\": \"^17.3.0\",\n-    \"@types/express\": \"^4.17.17\",\n-    \"@types/jasmine\": \"~5.1.0\",\n-    \"@types/node\": \"^18.18.0\",\n-    \"jasmine-core\": \"~5.1.0\",\n+    \"@angular-devkit/build-angular\": \"^16.2.5\",\n+    \"@angular/cli\": \"^16.2.5\",\n+    \"@angular/compiler-cli\": \"^16.2.0\",\n+    \"@types/jasmine\": \"~4.3.0\",\n+    \"jasmine-core\": \"~4.6.0\",\n     \"karma\": \"~6.4.0\",\n     \"karma-chrome-launcher\": \"~3.2.0\",\n     \"karma-coverage\": \"~2.2.0\",\n     \"karma-jasmine\": \"~5.1.0\",\n     \"karma-jasmine-html-reporter\": \"~2.1.0\",\n-    \"typescript\": \"~5.4.2\"\n+    \"typescript\": \"~5.1.3\"\n   }\n }\n"
                },
                {
                    "date": 1722111996887,
                    "content": "Index: \n===================================================================\n--- \n+++ \n@@ -11,9 +11,9 @@\n   \"private\": true,\n   \"dependencies\": {\n     \"@angular/animations\": \"^16.2.0\",\n     \"@angular/cdk\": \"^16.2.7\",\n-    \"@angular/common\": \"^16.2.0\",\n+    \"@angular/common\": \"^17.0.0\",\n     \"@angular/compiler\": \"^16.2.0\",\n     \"@angular/core\": \"^16.2.0\",\n     \"@angular/flex-layout\": \"^15.0.0-beta.42\",\n     \"@angular/forms\": \"^16.2.0\",\n"
                },
                {
                    "date": 1722112195858,
                    "content": "Index: \n===================================================================\n--- \n+++ \n@@ -0,0 +1,46 @@\n+{\n+  \"name\": \"taxt-backend\",\n+  \"version\": \"0.0.0\",\n+  \"scripts\": {\n+    \"ng\": \"ng\",\n+    \"start\": \"ng serve\",\n+    \"build\": \"ng build\",\n+    \"watch\": \"ng build --watch --configuration development\",\n+    \"test\": \"ng test\"\n+  },\n+  \"private\": true,\n+  \"dependencies\": {\n+    \"@angular/animations\": \"^16.2.0\",\n+    \"@angular/cdk\": \"^16.2.14\",\n+    \"@angular/common\": \"^17.0.0\",\n+    \"@angular/compiler\": \"^16.2.0\",\n+    \"@angular/core\": \"^16.2.0\",\n+    \"@angular/flex-layout\": \"^15.0.0-beta.42\",\n+    \"@angular/forms\": \"^16.2.0\",\n+    \"@angular/google-maps\": \"^17.0.1\",\n+    \"@angular/material\": \"^16.2.7\",\n+    \"@angular/platform-browser\": \"^16.2.0\",\n+    \"@angular/platform-browser-dynamic\": \"^16.2.0\",\n+    \"@angular/router\": \"^16.2.0\",\n+    \"@types/socket.io-client\": \"^3.0.0\",\n+    \"core-js\": \"^3.33.2\",\n+    \"moment-timezone\": \"^0.5.43\",\n+    \"rxjs\": \"~7.8.0\",\n+    \"rxjs-compat\": \"^6.6.7\",\n+    \"tslib\": \"^2.3.0\",\n+    \"zone.js\": \"~0.13.0\"\n+  },\n+  \"devDependencies\": {\n+    \"@angular-devkit/build-angular\": \"^16.2.5\",\n+    \"@angular/cli\": \"^16.2.5\",\n+    \"@angular/compiler-cli\": \"^16.2.0\",\n+    \"@types/jasmine\": \"~4.3.0\",\n+    \"jasmine-core\": \"~4.6.0\",\n+    \"karma\": \"~6.4.0\",\n+    \"karma-chrome-launcher\": \"~3.2.0\",\n+    \"karma-coverage\": \"~2.2.0\",\n+    \"karma-jasmine\": \"~5.1.0\",\n+    \"karma-jasmine-html-reporter\": \"~2.1.0\",\n+    \"typescript\": \"~5.1.3\"\n+  }\n+}\n"
                },
                {
                    "date": 1722112737062,
                    "content": "Index: \n===================================================================\n--- \n+++ \n@@ -5,88 +5,49 @@\n     \"ng\": \"ng\",\n     \"start\": \"ng serve\",\n     \"build\": \"ng build\",\n     \"watch\": \"ng build --watch --configuration development\",\n-    \"test\": \"ng test\"\n+    \"test\": \"ng test\",\n+    \"serve:ssr:taxt-Backend\": \"node dist/taxt-backend/server/server.mjs\"\n   },\n   \"private\": true,\n   \"dependencies\": {\n-    \"@angular/animations\": \"^16.2.0\",\n-    \"@angular/cdk\": \"^16.2.14\",\n-    \"@angular/common\": \"^17.0.0\",\n-    \"@angular/compiler\": \"^16.2.0\",\n-    \"@angular/core\": \"^16.2.0\",\n+    \"@angular/animations\": \"^17.3.0\",\n+    \"@angular/cdk\": \"^17.3.10\",\n+    \"@angular/common\": \"^17.3.0\",\n+    \"@angular/compiler\": \"^17.3.0\",\n+    \"@angular/core\": \"^17.3.0\",\n     \"@angular/flex-layout\": \"^15.0.0-beta.42\",\n-    \"@angular/forms\": \"^16.2.0\",\n-    \"@angular/google-maps\": \"^17.0.1\",\n-    \"@angular/material\": \"^16.2.7\",\n-    \"@angular/platform-browser\": \"^16.2.0\",\n-    \"@angular/platform-browser-dynamic\": \"^16.2.0\",\n-    \"@angular/router\": \"^16.2.0\",\n+    \"@angular/forms\": \"^17.3.0\",\n+    \n+    \"@angular/material\": \"^17.3.10\",\n+    \"@angular/platform-browser\": \"^17.3.0\",\n+    \"@angular/platform-browser-dynamic\": \"^17.3.0\",\n+    \"@angular/platform-server\": \"^17.3.0\",\n+     \"@angular/router\": \"^17.3.0\",\n+    \"@angular/ssr\": \"^17.3.8\",\n     \"@types/socket.io-client\": \"^3.0.0\",\n-    \"core-js\": \"^3.33.2\",\n-    \"moment-timezone\": \"^0.5.43\",\n+    \"core-js\": \"^3.37.1\",\n+    \"express\": \"^4.18.2\",\n+    \"moment-timezone\": \"^0.5.45\",\n     \"rxjs\": \"~7.8.0\",\n     \"rxjs-compat\": \"^6.6.7\",\n     \"tslib\": \"^2.3.0\",\n-    \"zone.js\": \"~0.13.0\"\n+    \"zone.js\": \"~0.14.3\"\n   },\n   \"devDependencies\": {\n-    \"@angular-devkit/build-angular\": \"^16.2.5\",\n-    \"@angular/cli\": \"^16.2.5\",\n-    \"@angular/compiler-cli\": \"^16.2.0\",\n-    \"@types/jasmine\": \"~4.3.0\",\n-    \"jasmine-core\": \"~4.6.0\",\n+    \"@angular-devkit/build-angular\": \"^17.3.8\",\n+    \"@angular/cli\": \"^17.3.8\",\n+    \"@angular/compiler-cli\": \"^17.3.0\",\n+    \"@types/express\": \"^4.17.17\",\n+    \"@types/jasmine\": \"~5.1.0\",\n+    \"@types/node\": \"^18.18.0\",\n+    \"jasmine-core\": \"~5.1.0\",\n     \"karma\": \"~6.4.0\",\n     \"karma-chrome-launcher\": \"~3.2.0\",\n     \"karma-coverage\": \"~2.2.0\",\n     \"karma-jasmine\": \"~5.1.0\",\n     \"karma-jasmine-html-reporter\": \"~2.1.0\",\n-    \"typescript\": \"~5.1.3\"\n+    \"typescript\": \"~5.4.2\"\n   }\n }\n-{\n-  \"name\": \"taxt-backend\",\n-  \"version\": \"0.0.0\",\n-  \"scripts\": {\n-    \"ng\": \"ng\",\n-    \"start\": \"ng serve\",\n-    \"build\": \"ng build\",\n-    \"watch\": \"ng build --watch --configuration development\",\n-    \"test\": \"ng test\"\n-  },\n-  \"private\": true,\n-  \"dependencies\": {\n-    \"@angular/animations\": \"^16.2.0\",\n-    \"@angular/cdk\": \"^16.2.7\",\n-    \"@angular/common\": \"^17.0.0\",\n-    \"@angular/compiler\": \"^16.2.0\",\n-    \"@angular/core\": \"^16.2.0\",\n-    \"@angular/flex-layout\": \"^15.0.0-beta.42\",\n-    \"@angular/forms\": \"^16.2.0\",\n-    \"@angular/google-maps\": \"^17.0.1\",\n-    \"@angular/material\": \"^16.2.7\",\n-    \"@angular/platform-browser\": \"^16.2.0\",\n-    \"@angular/platform-browser-dynamic\": \"^16.2.0\",\n-    \"@angular/router\": \"^16.2.0\",\n-    \"@types/socket.io-client\": \"^3.0.0\",\n-    \"core-js\": \"^3.33.2\",\n-    \"moment-timezone\": \"^0.5.43\",\n-    \"rxjs\": \"~7.8.0\",\n-    \"rxjs-compat\": \"^6.6.7\",\n-    \"tslib\": \"^2.3.0\",\n-    \"zone.js\": \"~0.13.0\"\n-  },\n-  \"devDependencies\": {\n-    \"@angular-devkit/build-angular\": \"^16.2.5\",\n-    \"@angular/cli\": \"^16.2.5\",\n-    \"@angular/compiler-cli\": \"^16.2.0\",\n-    \"@types/jasmine\": \"~4.3.0\",\n-    \"jasmine-core\": \"~4.6.0\",\n-    \"karma\": \"~6.4.0\",\n-    \"karma-chrome-launcher\": \"~3.2.0\",\n-    \"karma-coverage\": \"~2.2.0\",\n-    \"karma-jasmine\": \"~5.1.0\",\n-    \"karma-jasmine-html-reporter\": \"~2.1.0\",\n-    \"typescript\": \"~5.1.3\"\n-  }\n-}\n+    \n"
                },
                {
                    "date": 1722140181494,
                    "content": "Index: \n===================================================================\n--- \n+++ \n@@ -17,14 +17,14 @@\n     \"@angular/compiler\": \"^17.3.0\",\n     \"@angular/core\": \"^17.3.0\",\n     \"@angular/flex-layout\": \"^15.0.0-beta.42\",\n     \"@angular/forms\": \"^17.3.0\",\n-    \n+    \"@angular/google-maps\": \"^18.1.2\",\n     \"@angular/material\": \"^17.3.10\",\n     \"@angular/platform-browser\": \"^17.3.0\",\n     \"@angular/platform-browser-dynamic\": \"^17.3.0\",\n     \"@angular/platform-server\": \"^17.3.0\",\n-     \"@angular/router\": \"^17.3.0\",\n+    \"@angular/router\": \"^17.3.0\",\n     \"@angular/ssr\": \"^17.3.8\",\n     \"@types/socket.io-client\": \"^3.0.0\",\n     \"core-js\": \"^3.37.1\",\n     \"express\": \"^4.18.2\",\n@@ -48,6 +48,6 @@\n     \"karma-jasmine\": \"~5.1.0\",\n     \"karma-jasmine-html-reporter\": \"~2.1.0\",\n     \"typescript\": \"~5.4.2\"\n   }\n+  \n }\n-    \n"
                }
            ],
            "date": 1721482424228,
            "name": "Commit-0",
            "content": "{\n  \"name\": \"taxt-backend\",\n  \"version\": \"0.0.0\",\n  \"scripts\": {\n    \"ng\": \"ng\",\n    \"start\": \"ng serve\",\n    \"build\": \"ng build\",\n    \"watch\": \"ng build --watch --configuration development\",\n    \"test\": \"ng test\",\n    \"serve:ssr:taxt-Backend\": \"node dist/taxt-backend/server/server.mjs\"\n  },\n  \"private\": true,\n  \"dependencies\": {\n    \"@angular/animations\": \"^17.3.0\",\n    \"@angular/cdk\": \"^17.3.10\",\n    \"@angular/common\": \"^17.3.0\",\n    \"@angular/compiler\": \"^17.3.0\",\n    \"@angular/core\": \"^17.3.0\",\n    \"@angular/flex-layout\": \"^15.0.0-beta.42\",\n    \"@angular/forms\": \"^17.3.0\",\n    \"@angular/material\": \"^17.3.10\",\n    \"@angular/platform-browser\": \"^17.3.0\",\n    \"@angular/platform-browser-dynamic\": \"^17.3.0\",\n    \"@angular/platform-server\": \"^17.3.0\",\n    \"@angular/router\": \"^17.3.0\",\n    \"@angular/ssr\": \"^17.3.8\",\n    \"@types/socket.io-client\": \"^3.0.0\",\n    \"core-js\": \"^3.37.1\",\n    \"express\": \"^4.18.2\",\n    \"moment-timezone\": \"^0.5.45\",\n    \"rxjs\": \"~7.8.0\",\n    \"rxjs-compat\": \"^6.6.7\",\n    \"tslib\": \"^2.3.0\",\n    \"zone.js\": \"~0.14.3\"\n  },\n  \"devDependencies\": {\n    \"@angular-devkit/build-angular\": \"^17.3.8\",\n    \"@angular/cli\": \"^17.3.8\",\n    \"@angular/compiler-cli\": \"^17.3.0\",\n    \"@types/express\": \"^4.17.17\",\n    \"@types/jasmine\": \"~5.1.0\",\n    \"@types/node\": \"^18.18.0\",\n    \"jasmine-core\": \"~5.1.0\",\n    \"karma\": \"~6.4.0\",\n    \"karma-chrome-launcher\": \"~3.2.0\",\n    \"karma-coverage\": \"~2.2.0\",\n    \"karma-jasmine\": \"~5.1.0\",\n    \"karma-jasmine-html-reporter\": \"~2.1.0\",\n    \"typescript\": \"~5.4.2\"\n  }\n}\n"
        }
    ]
}